vibhaga/__init__.py
vibhaga/inspector.py
vibhaga_keremkoseoglu-0.2.1.dist-info/METADATA
vibhaga_keremkoseoglu-0.2.1.dist-info/WHEEL
vibhaga_keremkoseoglu-0.2.1.dist-info/top_level.txt
vibhaga_keremkoseoglu-0.2.1.dist-info/RECORD
