Metadata-Version: 2.1
Name: vibhaga-keremkoseoglu
Version: 0.2.1
Summary: Vibhaga is a dynamic module loader for Python
Home-page: https://github.com/keremkoseoglu/vibhaga
Author: Kerem Koseoglu
Author-email: kerem@keremkoseoglu.com
License: UNKNOWN
Platform: UNKNOWN
Classifier: Programming Language :: Python :: 3
Classifier: License :: OSI Approved :: MIT License
Classifier: Operating System :: OS Independent
Requires-Python: >=3.6.5
